aiFlow/__init__.py
aiFlow/perceptron.py
aiFlow_pypi_Hassi34-0.0.1.dist-info/LICENSE
aiFlow_pypi_Hassi34-0.0.1.dist-info/METADATA
aiFlow_pypi_Hassi34-0.0.1.dist-info/WHEEL
aiFlow_pypi_Hassi34-0.0.1.dist-info/top_level.txt
aiFlow_pypi_Hassi34-0.0.1.dist-info/RECORD
