Metadata-Version: 2.1
Name: aiFlow-pypi-Hassi34
Version: 0.0.1
Summary: It's an Implimentation of Perceptron
Home-page: https://github.com/Hassi34/aiFlow_pypi
Author: Hassi34
Author-email: hasnainmehmood3435@gmail.com
License: UNKNOWN
Project-URL: Bug Tracker, https://github.com/Hassi34/aiFlow_pypi/issues
Platform: UNKNOWN
Classifier: Programming Language :: Python :: 3
Classifier: License :: OSI Approved :: MIT License
Classifier: Operating System :: OS Independent
Requires-Python: >=3.7
License-File: LICENSE
Requires-Dist: numpy
Requires-Dist: tqdm
